Workbook

Sheet characters
A1: Name | B1: Pronouns | C1: Gender | D1: Birthday | E1: Class | F1: House | G1: Height (cm) | H1: Skin | I1: Hair | J1: Eyes | K1: Best Friends | L1: Close Friends | M1: Frenemies/Rivals | N1: Romantic Interest | O1: Personality Strengths | P1: Personality Weaknesses | Q1: Tier | R1: HP | S1: DEF | T1: ATK | U1: MAG | V1: AGI | W1: INT | X1: Total | Y1: Max Mana | Z1: Mana Regen
A2: Alanza Alves | B2: she/her | C2: Cis female | D2: 37409 | E2: Warlock | F2: Hufflepuff | G2: 170 | H2: Dark brown | I2: Long straight brown (middle part) | J2: Brown | K2: Liz, Barnaby | L2: Chiara, Ben | M2: - | N2: Unknown | O2: Gifted, Adaptable, Warm-hearted, Resilient, Empathetic, Mysterious, Distinct, Observant, Adventure-linked, Bond-oriented | P2: Secretive, Elusive, Burdened, Overprotective, Cautious to trust | Q2: =VLOOKUP(characters[[#This Row],[Class]],stats!$A:$I,2,FALSE) -> A | R2: =(VLOOKUP(characters[[#This Row],[Class]],stats!$A:$I,3,FALSE))*10 -> 550 | S2: =VLOOKUP(characters[[#This Row],[Class]],stats!$A:$I,4,FALSE) -> 40 | T2: =VLOOKUP(characters[[#This Row],[Class]],stats!$A:$I,5,FALSE) -> 30 | U2: =VLOOKUP(characters[[#This Row],[Class]],stats!$A:$I,6,FALSE) -> 90 | V2: =VLOOKUP(characters[[#This Row],[Class]],stats!$A:$I,7,FALSE) -> 65 | W2: =VLOOKUP(characters[[#This Row],[Class]],stats!$A:$I,8,FALSE) -> 75 | X2: =VLOOKUP(characters[[#This Row],[Class]],stats!$A:$I,9,FALSE) -> 355 | Y2: =ROUND(50+(VLOOKUP(E2,stats!$A:$I,8,0)*0.5),0) -> 88 | Z2: =ROUND(VLOOKUP(E2,stats!$A:$I,8,0)*0.1,0) -> 8 | AB2: 10
A3: Andre Egwu | B3: he/they | C3: Demiboy | D3: 36692 | E3: Bard | F3: Ravenclaw | G3: 171 | H3: Dark brown | I3: Buzz cut | J3: Brown | K3: Talbott | L3: Tulip, Hayami | M3: - | N3: Talbott | O3: Romantic, Compassionate, Inspiring, Optimistic, Caring, Dreamy, Hopeful, Soft-spoken, Sensitive | P3: Naïve, Over-emotional, Unrealistic, Idealistic to a fault, Overly sentimental, Impressionable | Q3: =VLOOKUP(characters[[#This Row],[Class]],stats!$A:$I,2,FALSE) -> C | R3: =(VLOOKUP(characters[[#This Row],[Class]],stats!$A:$I,3,FALSE))*10 -> 600 | S3: =VLOOKUP(characters[[#This Row],[Class]],stats!$A:$I,4,FALSE) -> 45 | T3: =VLOOKUP(characters[[#This Row],[Class]],stats!$A:$I,5,FALSE) -> 30 | U3: =VLOOKUP(characters[[#This Row],[Class]],stats!$A:$I,6,FALSE) -> 80 | V3: =VLOOKUP(characters[[#This Row],[Class]],stats!$A:$I,7,FALSE) -> 55 | W3: =VLOOKUP(characters[[#This Row],[Class]],stats!$A:$I,8,FALSE) -> 85 | X3: =VLOOKUP(characters[[#This Row],[Class]],stats!$A:$I,9,FALSE) -> 355 | Y3: =ROUND(50+(VLOOKUP(E3,stats!$A:$I,8,0)*0.5),0) -> 93 | Z3: =ROUND(VLOOKUP(E3,stats!$A:$I,8,0)*0.1,0) -> 9
A4: Badeea Ali | B4: she/her | C4: Cis female | D4: 37176 | E4: Necromancer | F4: Ravenclaw | G4: 169 | H4: Pale | I4: Black (covered by hijab) | J4: Brown | K4: Rowan | L4: Talbott, Orion | M4: - | N4: Orion | O4: Creative, Imaginative, Calm, Inspiring, Innovative, Art-driven, Unconventional, Visual thinker, Expressive, Aesthetic-focused | P4: Withdrawn, Overly introspective, Sensitive to criticism, Perfectionistic, Conflict-avoidant | Q4: =VLOOKUP(characters[[#This Row],[Class]],stats!$A:$I,2,FALSE) -> A | R4: =(VLOOKUP(characters[[#This Row],[Class]],stats!$A:$I,3,FALSE))*10 -> 550 | S4: =VLOOKUP(characters[[#This Row],[Class]],stats!$A:$I,4,FALSE) -> 40 | T4: =VLOOKUP(characters[[#This Row],[Class]],stats!$A:$I,5,FALSE) -> 25 | U4: =VLOOKUP(characters[[#This Row],[Class]],stats!$A:$I,6,FALSE) -> 90 | V4: =VLOOKUP(characters[[#This Row],[Class]],stats!$A:$I,7,FALSE) -> 45 | W4: =VLOOKUP(characters[[#This Row],[Class]],stats!$A:$I,8,FALSE) -> 95 | X4: =VLOOKUP(characters[[#This Row],[Class]],stats!$A:$I,9,FALSE) -> 350 | Y4: =ROUND(50+(VLOOKUP(E4,stats!$A:$I,8,0)*0.5),0) -> 98 | Z4: =ROUND(VLOOKUP(E4,stats!$A:$I,8,0)*0.1,0) -> 10
A5: Barnaby Lee | B5: he/him | C5: Cis male | D5: 36933 | E5: Fighter | F5: Slytherin | G5: 176 | H5: Fair | I5: Short brown | J5: Green | K5: Liz, Alanza | L5: Mayumi, Chiara, Penny, Badeea | M5: - | N5: Ben or Penny | O5: Mediator, Diplomatic, Empathetic, Patient, Harmonious, Tactful, Calm, Adaptable, Sensitive to others | P5: Avoidant, People-pleasing, Passive, Indecisive, Conflict-averse, Non-confrontational | Q5: =VLOOKUP(characters[[#This Row],[Class]],stats!$A:$I,2,FALSE) -> B | R5: =(VLOOKUP(characters[[#This Row],[Class]],stats!$A:$I,3,FALSE))*10 -> 900 | S5: =VLOOKUP(characters[[#This Row],[Class]],stats!$A:$I,4,FALSE) -> 85 | T5: =VLOOKUP(characters[[#This Row],[Class]],stats!$A:$I,5,FALSE) -> 80 | U5: =VLOOKUP(characters[[#This Row],[Class]],stats!$A:$I,6,FALSE) -> 15 | V5: =VLOOKUP(characters[[#This Row],[Class]],stats!$A:$I,7,FALSE) -> 45 | W5: =VLOOKUP(characters[[#This Row],[Class]],stats!$A:$I,8,FALSE) -> 35 | X5: =VLOOKUP(characters[[#This Row],[Class]],stats!$A:$I,9,FALSE) -> 350 | Y5: =ROUND(50+(VLOOKUP(E5,stats!$A:$I,8,0)*0.5),0) -> 68 | Z5: =ROUND(VLOOKUP(E5,stats!$A:$I,8,0)*0.1,0) -> 4
A6: Ben Copper | B6: he/they | C6: Demiboy | D6: 37166 | E6: Oracle | F6: Gryffindor | G6: 169 | H6: Medium | I6: Short sandy blonde | J6: Brown | K6: Rowan | L6: Liam, Jae, Barnaby | M6: - | N6: Rowan or Barnaby | O6: Insightful, Detail-oriented, Observant, Cautious, Thorough, Methodical, Skeptical, Introspective | P6: Overthinker, Paranoid, Pessimistic, Distrustful, Aloof, Calculating, Reticent | Q6: =VLOOKUP(characters[[#This Row],[Class]],stats!$A:$I,2,FALSE) -> B | R6: =(VLOOKUP(characters[[#This Row],[Class]],stats!$A:$I,3,FALSE))*10 -> 550 | S6: =VLOOKUP(characters[[#This Row],[Class]],stats!$A:$I,4,FALSE) -> 45 | T6: =VLOOKUP(characters[[#This Row],[Class]],stats!$A:$I,5,FALSE) -> 20 | U6: =VLOOKUP(characters[[#This Row],[Class]],stats!$A:$I,6,FALSE) -> 70 | V6: =VLOOKUP(characters[[#This Row],[Class]],stats!$A:$I,7,FALSE) -> 50 | W6: =VLOOKUP(characters[[#This Row],[Class]],stats!$A:$I,8,FALSE) -> 90 | X6: =VLOOKUP(characters[[#This Row],[Class]],stats!$A:$I,9,FALSE) -> 330 | Y6: =ROUND(50+(VLOOKUP(E6,stats!$A:$I,8,0)*0.5),0) -> 95 | Z6: =ROUND(VLOOKUP(E6,stats!$A:$I,8,0)*0.1,0) -> 9
A7: Chiara Lobosca | B7: she/her | C7: Cis female | D7: 37237 | E7: Cleric | F7: Hufflepuff | G7: 163 | H7: Pale | I7: White bob | J7: Yellow | K7: Mayumi | L7: Penny, Barnaby, Viktor, Alanza | M7: - | N7: Mayumi | O7: Compassionate, Patient, Generous, Understanding, Caring, Sensitive, Protective, Dependable, Soft-spoken, Warm-hearted | P7: Overbearing, Self-sacrificing, Overly emotional, Easily drained, Codependent | Q7: =VLOOKUP(characters[[#This Row],[Class]],stats!$A:$I,2,FALSE) -> B | R7: =(VLOOKUP(characters[[#This Row],[Class]],stats!$A:$I,3,FALSE))*10 -> 700 | S7: =VLOOKUP(characters[[#This Row],[Class]],stats!$A:$I,4,FALSE) -> 65 | T7: =VLOOKUP(characters[[#This Row],[Class]],stats!$A:$I,5,FALSE) -> 40 | U7: =VLOOKUP(characters[[#This Row],[Class]],stats!$A:$I,6,FALSE) -> 80 | V7: =VLOOKUP(characters[[#This Row],[Class]],stats!$A:$I,7,FALSE) -> 40 | W7: =VLOOKUP(characters[[#This Row],[Class]],stats!$A:$I,8,FALSE) -> 60 | X7: =VLOOKUP(characters[[#This Row],[Class]],stats!$A:$I,9,FALSE) -> 355 | Y7: =ROUND(50+(VLOOKUP(E7,stats!$A:$I,8,0)*0.5),0) -> 80 | Z7: =ROUND(VLOOKUP(E7,stats!$A:$I,8,0)*0.1,0) -> 6
A8: Diego Caplan | B8: he/him | C8: Cis male | D8: 36776 | E8: Monk | F8: Hufflepuff | G8: 173 | H8: Medium | I8: Shaggy brown (covers nape) | J8: Brown | K8: Jae | L8: Barnaby, Andre, Penny | M8: Liam, Hayami, Merula (frenemies) | N8: Unknown | O8: Enthusiastic, Brave, Supportive, Respectful, Motivating, Adventurous, Challenge-driven, Action-oriented, Storyteller, High-energy | P8: Overcompetitive, Impulsive, Overconfident, Restless, Flirtatious | Q8: =VLOOKUP(characters[[#This Row],[Class]],stats!$A:$I,2,FALSE) -> C | R8: =(VLOOKUP(characters[[#This Row],[Class]],stats!$A:$I,3,FALSE))*10 -> 700 | S8: =VLOOKUP(characters[[#This Row],[Class]],stats!$A:$I,4,FALSE) -> 60 | T8: =VLOOKUP(characters[[#This Row],[Class]],stats!$A:$I,5,FALSE) -> 80 | U8: =VLOOKUP(characters[[#This Row],[Class]],stats!$A:$I,6,FALSE) -> 25 | V8: =VLOOKUP(characters[[#This Row],[Class]],stats!$A:$I,7,FALSE) -> 85 | W8: =VLOOKUP(characters[[#This Row],[Class]],stats!$A:$I,8,FALSE) -> 30 | X8: =VLOOKUP(characters[[#This Row],[Class]],stats!$A:$I,9,FALSE) -> 350 | Y8: =ROUND(50+(VLOOKUP(E8,stats!$A:$I,8,0)*0.5),0) -> 65 | Z8: =ROUND(VLOOKUP(E8,stats!$A:$I,8,0)*0.1,0) -> 3
A9: Emily Tyler | B9: she/her | C9: Cis female | D9: 36220 | E9: Anti-Paladin | F9: Gryffindor | G9: 168 | H9: Fair | I9: Long dark brown ponytail | J9: Dark brown | K9: - | L9: Erika | M9: Liam, Penny (frenemies) | N9: Unknown | O9: Brave, Bold, Confident, Assertive, Resilient, Ambitious, Strategic, Independent, Competitive | P9: Haughty, Elitist, Intimidating, Controlling, Cocky, Image-conscious | Q9: =VLOOKUP(characters[[#This Row],[Class]],stats!$A:$I,2,FALSE) -> B | R9: =(VLOOKUP(characters[[#This Row],[Class]],stats!$A:$I,3,FALSE))*10 -> 800 | S9: =VLOOKUP(characters[[#This Row],[Class]],stats!$A:$I,4,FALSE) -> 75 | T9: =VLOOKUP(characters[[#This Row],[Class]],stats!$A:$I,5,FALSE) -> 85 | U9: =VLOOKUP(characters[[#This Row],[Class]],stats!$A:$I,6,FALSE) -> 35 | V9: =VLOOKUP(characters[[#This Row],[Class]],stats!$A:$I,7,FALSE) -> 35 | W9: =VLOOKUP(characters[[#This Row],[Class]],stats!$A:$I,8,FALSE) -> 50 | X9: =VLOOKUP(characters[[#This Row],[Class]],stats!$A:$I,9,FALSE) -> 355 | Y9: =ROUND(50+(VLOOKUP(E9,stats!$A:$I,8,0)*0.5),0) -> 75 | Z9: =ROUND(VLOOKUP(E9,stats!$A:$I,8,0)*0.1,0) -> 5
A10: Erika Rath | B10: she/her | C10: Cis female | D10: 36388 | E10: Paladin | F10: Slytherin | G10: 169 | H10: Pale | I10: Long straight blonde (bang slicked back) | J10: Blue | K10: - | L10: Emily | M10: Skye, Liam, Hayami (frenemies) | N10: Unknown | O10: Skilled, Confident, Determined, Loyal (to the worthy), Disciplined, Competitive, Selective, Intensity-focused, Respect-oriented | P10: Arrogant, Confrontational, Intolerant to weakness, Emotionally closed-off, Domineering, Pride-driven | Q10: =VLOOKUP(characters[[#This Row],[Class]],stats!$A:$I,2,FALSE) -> B | R10: =(VLOOKUP(characters[[#This Row],[Class]],stats!$A:$I,3,FALSE))*10 -> 800 | S10: =VLOOKUP(characters[[#This Row],[Class]],stats!$A:$I,4,FALSE) -> 90 | T10: =VLOOKUP(characters[[#This Row],[Class]],stats!$A:$I,5,FALSE) -> 80 | U10: =VLOOKUP(characters[[#This Row],[Class]],stats!$A:$I,6,FALSE) -> 55 | V10: =VLOOKUP(characters[[#This Row],[Class]],stats!$A:$I,7,FALSE) -> 35 | W10: =VLOOKUP(characters[[#This Row],[Class]],stats!$A:$I,8,FALSE) -> 45 | X10: =VLOOKUP(characters[[#This Row],[Class]],stats!$A:$I,9,FALSE) -> 360 | Y10: =ROUND(50+(VLOOKUP(E10,stats!$A:$I,8,0)*0.5),0) -> 73 | Z10: =ROUND(VLOOKUP(E10,stats!$A:$I,8,0)*0.1,0) -> 5
A11: Hayami Amamiya | B11: she/he/they | C11: Agender | D11: 37336 | E11: Druid | F11: Ravenclaw | G11: 173 | H11: Pale | I11: Short blonde wolf cut | J11: Green | K11: Tulip | L11: Talbott, Andre, Mayumi, Orion, Skye | M11: Merula (dislike) / Tulip (healthy rival) | N11: Tulip | O11: Loyal, Honest, Protective, Insightful, Independent, Reserved, Analytical, Witty | P11: Cynical, Sarcastic, Distrustful, Jaded, Blunt, Skeptical | Q11: =VLOOKUP(characters[[#This Row],[Class]],stats!$A:$I,2,FALSE) -> S | R11: =(VLOOKUP(characters[[#This Row],[Class]],stats!$A:$I,3,FALSE))*10 -> 900 | S11: =VLOOKUP(characters[[#This Row],[Class]],stats!$A:$I,4,FALSE) -> 90 | T11: =VLOOKUP(characters[[#This Row],[Class]],stats!$A:$I,5,FALSE) -> 93 | U11: =VLOOKUP(characters[[#This Row],[Class]],stats!$A:$I,6,FALSE) -> 95 | V11: =VLOOKUP(characters[[#This Row],[Class]],stats!$A:$I,7,FALSE) -> 95 | W11: =VLOOKUP(characters[[#This Row],[Class]],stats!$A:$I,8,FALSE) -> 95 | X11: =VLOOKUP(characters[[#This Row],[Class]],stats!$A:$I,9,FALSE) -> 565 | Y11: =ROUND(50+(VLOOKUP(E11,stats!$A:$I,8,0)*0.5),0) -> 98 | Z11: =ROUND(VLOOKUP(E11,stats!$A:$I,8,0)*0.1,0) -> 10
A12: Ismelda Mulk | B12: she/her | C12: Cis female | D12: 36949 | E12: Blood Hunter | F12: Slytherin | G12: 166 | H12: Pale | I12: Shoulder-length black with blue dyed ends | J12: Golden | K12: Merula | L12: Barnaby | M12: - | N12: Unknown | O12: Determined, Courageous, Loyal, Mentoring, Driven, Intense, Athletic, Growth-oriented | P12: Impulsive, Overcompetitive, Quick to judge, Self-doubting, Inconsistent, Legacy-focused, Emotionally reactive | Q12: =VLOOKUP(characters[[#This Row],[Class]],stats!$A:$I,2,FALSE) -> A | R12: =(VLOOKUP(characters[[#This Row],[Class]],stats!$A:$I,3,FALSE))*10 -> 750 | S12: =VLOOKUP(characters[[#This Row],[Class]],stats!$A:$I,4,FALSE) -> 60 | T12: =VLOOKUP(characters[[#This Row],[Class]],stats!$A:$I,5,FALSE) -> 88 | U12: =VLOOKUP(characters[[#This Row],[Class]],stats!$A:$I,6,FALSE) -> 45 | V12: =VLOOKUP(characters[[#This Row],[Class]],stats!$A:$I,7,FALSE) -> 65 | W12: =VLOOKUP(characters[[#This Row],[Class]],stats!$A:$I,8,FALSE) -> 70 | X12: =VLOOKUP(characters[[#This Row],[Class]],stats!$A:$I,9,FALSE) -> 388 | Y12: =ROUND(50+(VLOOKUP(E12,stats!$A:$I,8,0)*0.5),0) -> 85 | Z12: =ROUND(VLOOKUP(E12,stats!$A:$I,8,0)*0.1,0) -> 7
A13: Jacob Quinn | B13: he/him | C13: Cis male | D13: 36405 | E13: Gunslinger | F13: Gryffindor | G13: 177 | H13: Dark | I13: Buzz cut | J13: Blue | K13: Liam | L13: - | M13: - | N13: Unknown | O13: Ambitious, Intelligent, Resourceful, Charismatic, Loyal, Adventurous, Independent, Determined, Persuasive | P13: Reckless, Rule-breaking, Defiant, Secretive, Curious | Q13: =VLOOKUP(characters[[#This Row],[Class]],stats!$A:$I,2,FALSE) -> C | R13: =(VLOOKUP(characters[[#This Row],[Class]],stats!$A:$I,3,FALSE))*10 -> 600 | S13: =VLOOKUP(characters[[#This Row],[Class]],stats!$A:$I,4,FALSE) -> 45 | T13: =VLOOKUP(characters[[#This Row],[Class]],stats!$A:$I,5,FALSE) -> 85 | U13: =VLOOKUP(characters[[#This Row],[Class]],stats!$A:$I,6,FALSE) -> 20 | V13: =VLOOKUP(characters[[#This Row],[Class]],stats!$A:$I,7,FALSE) -> 85 | W13: =VLOOKUP(characters[[#This Row],[Class]],stats!$A:$I,8,FALSE) -> 60 | X13: =VLOOKUP(characters[[#This Row],[Class]],stats!$A:$I,9,FALSE) -> 355 | Y13: =ROUND(50+(VLOOKUP(E13,stats!$A:$I,8,0)*0.5),0) -> 80 | Z13: =ROUND(VLOOKUP(E13,stats!$A:$I,8,0)*0.1,0) -> 6
A14: Jae Kim | B14: he/him | C14: Cis male | D14: 37080 | E14: Rogue | F14: Gryffindor | G14: 171 | H14: Fair | I14: Messy short black | J14: Brown | K14: Liam | L14: Ben, Rowan, Penny, Diego | M14: Merula | N14: Liam or Merula | O14: Humorous, Charismatic, Optimistic, Playful, Supportive, Light-hearted, Entertaining | P14: Sarcastic, Dismissive, Distraction-prone, Insensitive, Avoidant, Impulsive, Jittery, Unpredictable | Q14: =VLOOKUP(characters[[#This Row],[Class]],stats!$A:$I,2,FALSE) -> C | R14: =(VLOOKUP(characters[[#This Row],[Class]],stats!$A:$I,3,FALSE))*10 -> 600 | S14: =VLOOKUP(characters[[#This Row],[Class]],stats!$A:$I,4,FALSE) -> 45 | T14: =VLOOKUP(characters[[#This Row],[Class]],stats!$A:$I,5,FALSE) -> 80 | U14: =VLOOKUP(characters[[#This Row],[Class]],stats!$A:$I,6,FALSE) -> 20 | V14: =VLOOKUP(characters[[#This Row],[Class]],stats!$A:$I,7,FALSE) -> 90 | W14: =VLOOKUP(characters[[#This Row],[Class]],stats!$A:$I,8,FALSE) -> 55 | X14: =VLOOKUP(characters[[#This Row],[Class]],stats!$A:$I,9,FALSE) -> 350 | Y14: =ROUND(50+(VLOOKUP(E14,stats!$A:$I,8,0)*0.5),0) -> 78 | Z14: =ROUND(VLOOKUP(E14,stats!$A:$I,8,0)*0.1,0) -> 6
... A25: Viktor Ketsueki | B25: he/him | C25: Cis male | D25: 36798 | E25: Assassin | F25: Slytherin | G25: 173 | H25: Very pale | I25: Slick back black | J25: Dark brown | K25: - | L25: Talbott, Mayumi, Chiara | M25: - | N25: Unknown | O25: Intelligent, Loyal, Calm, Dedicated, Protective, Mischievous, Humorous, Observant | P25: Emotionally guarded, Very selective, Rebellious, Very secretive, Self-isolating, Mysterious | Q25: =VLOOKUP(characters[[#This Row],[Class]],stats!$A:$I,2,FALSE) -> B | R25: =(VLOOKUP(characters[[#This Row],[Class]],stats!$A:$I,3,FALSE))*10 -> 650 | S25: =VLOOKUP(characters[[#This Row],[Class]],stats!$A:$I,4,FALSE) -> 55 | T25: =VLOOKUP(characters[[#This Row],[Class]],stats!$A:$I,5,FALSE) -> 90 | U25: =VLOOKUP(characters[[#This Row],[Class]],stats!$A:$I,6,FALSE) -> 20 | V25: =VLOOKUP(characters[[#This Row],[Class]],stats!$A:$I,7,FALSE) -> 92 | W25: =VLOOKUP(characters[[#This Row],[Class]],stats!$A:$I,8,FALSE) -> 65 | X25: =VLOOKUP(characters[[#This Row],[Class]],stats!$A:$I,9,FALSE) -> 387 | Y25: =ROUND(50+(VLOOKUP(E25,stats!$A:$I,8,0)*0.5),0) -> 83 | Z25: =ROUND(VLOOKUP(E25,stats!$A:$I,8,0)*0.1,0) -> 7

Sheet battlesetup
B1: Player 1 | E1: Player 2
B2: Slot 1 | C2: Alanza Alves | E2: Slot 1 | F2: Barnaby Lee
B3: Slot 2 | C3: Andre Egwu | E3: Slot 2 | F3: Ben Copper
B4: Slot 3 | C4: Badeea Ali | E4: Slot 3 | F4: Chiara Lobosca
B6: Name | C6: Class | D6: Tier | E6: HP | F6: DEF | G6: ATK | H6: MAG | I6: AGI | J6: INT | K6: Max Mana
A7: P1 Slot 1 | B7: =IF(C2="","",C2) -> Alanza Alves | C7: =IF(C2="","",VLOOKUP(C2,'characters'!$A:$Z,5,0)) -> Warlock | D7: =IF(C2="","",VLOOKUP(C2,'characters'!$A:$Z,17,0)) -> A | E7: =IF(C2="","",VLOOKUP(C2,'characters'!$A:$Z,18,0)) -> 550 | F7: =IF(C2="","",VLOOKUP(C2,'characters'!$A:$Z,19,0)) -> 40 | G7: =IF(C2="","",VLOOKUP(C2,'characters'!$A:$Z,20,0)) -> 30 | H7: =IF(C2="","",VLOOKUP(C2,'characters'!$A:$Z,21,0)) -> 90 | I7: =IF(C2="","",VLOOKUP(C2,'characters'!$A:$Z,22,0)) -> 65 | J7: =IF(C2="","",VLOOKUP(C2,'characters'!$A:$Z,23,0)) -> 75 | K7: =IF(C2="","",VLOOKUP(C2,'characters'!$A:$Z,25,0)) -> 88
A8: P1 Slot 2 | B8: =IF(C3="","",C3) -> Andre Egwu | C8: =IF(C3="","",VLOOKUP(C3,'characters'!$A:$Z,5,0)) -> Bard | D8: =IF(C3="","",VLOOKUP(C3,'characters'!$A:$Z,17,0)) -> C | E8: =IF(C3="","",VLOOKUP(C3,'characters'!$A:$Z,18,0)) -> 600 | F8: =IF(C3="","",VLOOKUP(C3,'characters'!$A:$Z,19,0)) -> 45 | G8: =IF(C3="","",VLOOKUP(C3,'characters'!$A:$Z,20,0)) -> 30 | H8: =IF(C3="","",VLOOKUP(C3,'characters'!$A:$Z,21,0)) -> 80 | I8: =IF(C3="","",VLOOKUP(C3,'characters'!$A:$Z,22,0)) -> 55 | J8: =IF(C3="","",VLOOKUP(C3,'characters'!$A:$Z,23,0)) -> 85 | K8: =IF(C3="","",VLOOKUP(C3,'characters'!$A:$Z,25,0)) -> 93
A9: P1 Slot 3 | B9: =IF(C4="","",C4) -> Badeea Ali | C9: =IF(C4="","",VLOOKUP(C4,'characters'!$A:$Z,5,0)) -> Necromancer | D9: =IF(C4="","",VLOOKUP(C4,'characters'!$A:$Z,17,0)) -> A | E9: =IF(C4="","",VLOOKUP(C4,'characters'!$A:$Z,18,0)) -> 550 | F9: =IF(C4="","",VLOOKUP(C4,'characters'!$A:$Z,19,0)) -> 40 | G9: =IF(C4="","",VLOOKUP(C4,'characters'!$A:$Z,20,0)) -> 25 | H9: =IF(C4="","",VLOOKUP(C4,'characters'!$A:$Z,21,0)) -> 90 | I9: =IF(C4="","",VLOOKUP(C4,'characters'!$A:$Z,22,0)) -> 45 | J9: =IF(C4="","",VLOOKUP(C4,'characters'!$A:$Z,23,0)) -> 95 | K9: =IF(C4="","",VLOOKUP(C4,'characters'!$A:$Z,25,0)) -> 98
A11: P2 Slot 1 | B11: =IF(F2="","",F2) -> Barnaby Lee | C11: =IF(F2="","",VLOOKUP(F2,'characters'!$A:$Z,5,0)) -> Fighter | D11: =IF(F2="","",VLOOKUP(F2,'characters'!$A:$Z,17,0)) -> B | E11: =IF(F2="","",VLOOKUP(F2,'characters'!$A:$Z,18,0)) -> 900 | F11: =IF(F2="","",VLOOKUP(F2,'characters'!$A:$Z,19,0)) -> 85 | G11: =IF(F2="","",VLOOKUP(F2,'characters'!$A:$Z,20,0)) -> 80 | H11: =IF(F2="","",VLOOKUP(F2,'characters'!$A:$Z,21,0)) -> 15 | I11: =IF(F2="","",VLOOKUP(F2,'characters'!$A:$Z,22,0)) -> 45 | J11: =IF(F2="","",VLOOKUP(F2,'characters'!$A:$Z,23,0)) -> 35 | K11: =IF(F2="","",VLOOKUP(F2,'characters'!$A:$Z,25,0)) -> 68
A12: P2 Slot 2 | B12: =IF(F3="","",F3) -> Ben Copper | C12: =IF(F3="","",VLOOKUP(F3,'characters'!$A:$Z,5,0)) -> Oracle | D12: =IF(F3="","",VLOOKUP(F3,'characters'!$A:$Z,17,0)) -> B | E12: =IF(F3="","",VLOOKUP(F3,'characters'!$A:$Z,18,0)) -> 550 | F12: =IF(F3="","",VLOOKUP(F3,'characters'!$A:$Z,19,0)) -> 45 | G12: =IF(F3="","",VLOOKUP(F3,'characters'!$A:$Z,20,0)) -> 20 | H12: =IF(F3="","",VLOOKUP(F3,'characters'!$A:$Z,21,0)) -> 70 | I12: =IF(F3="","",VLOOKUP(F3,'characters'!$A:$Z,22,0)) -> 50 | J12: =IF(F3="","",VLOOKUP(F3,'characters'!$A:$Z,23,0)) -> 90 | K12: =IF(F3="","",VLOOKUP(F3,'characters'!$A:$Z,25,0)) -> 95
A13: P2 Slot 3 | B13: =IF(F4="","",F4) -> Chiara Lobosca | C13: =IF(F4="","",VLOOKUP(F4,'characters'!$A:$Z,5,0)) -> Cleric | D13: =IF(F4="","",VLOOKUP(F4,'characters'!$A:$Z,17,0)) -> B | E13: =IF(F4="","",VLOOKUP(F4,'characters'!$A:$Z,18,0)) -> 700 | F13: =IF(F4="","",VLOOKUP(F4,'characters'!$A:$Z,19,0)) -> 65 | G13: =IF(F4="","",VLOOKUP(F4,'characters'!$A:$Z,20,0)) -> 40 | H13: =IF(F4="","",VLOOKUP(F4,'characters'!$A:$Z,21,0)) -> 80 | I13: =IF(F4="","",VLOOKUP(F4,'characters'!$A:$Z,22,0)) -> 40 | J13: =IF(F4="","",VLOOKUP(F4,'characters'!$A:$Z,23,0)) -> 60 | K13: =IF(F4="","",VLOOKUP(F4,'characters'!$A:$Z,25,0)) -> 80

Sheet battlefield
B1: TURN | C1: =N3 -> 1 | M1: P1 Active Slot | N1: 1 | P1: Active Skills
B2: ACTIVE PLAYER | C2: =IF(N4=1,"Player 1", "Player 2") -> Player 1 | M2: P2 Active Slot | N2: 1 | P2: Eldritch Blast
M3: Turn Number | N3: 1 | P3: Eye of the Patron
B4: Player 1 | H4: Player 2 | M4: Active Player | N4: 1 | P4: Hunger of Hadar
B5: Character | C5: =IF(N1=1,battlesetup!C2,IF(N1=2,battlesetup!C3,battlesetup!C4)) -> Alanza Alves | H5: Character | I5: =IF(N2=1,battlesetup!F2,IF(N2=2,battlesetup!F3,battlesetup!F4)) -> Barnaby Lee | M5: P1 Slot1 HP | N5: 550 | P5: Misty Escape
B6: Class | C6: =IF(C5="","",VLOOKUP(C5,'characters'!$A:$Z,5,0)) -> Warlock | H6: Class | I6: =IF(I5="","",VLOOKUP(I5,'characters'!$A:$Z,5,0)) -> Fighter | M6: P1 Slot2 HP | N6: 600 | P6: Hurl Through Hell
B7: HP | C7: =IF(N1=1,N5,IF(N1=2,N6,N7)) -> 550 | H7: HP | I7: =IF(N2=1,N8,IF(N2=2,N9,N10)) -> 900 | M7: P1 Slot3 HP | N7: 550
B8: Mana | C8: =IF(N1=1,N11, IF(N1=2,N12,N13)) -> 88 | H8: Mana | I8: =IF(N2=1,N14,IF(N2=2,N15,N16)) -> 68 | M8: P2 Slot1 HP | N8: 900
M9: P2 Slot2 HP | N9: 550
M10: P2 Slot3 HP | N10: 700
B11: PARTY STATUS | H11: PARTY STATUS | M11: P1 Slot1 Mana | N11: 88
B12: Slot 1 | C12: =battlesetup!C2 -> Alanza Alves | D12: HP | E12: =N5 -> 550 | H12: Slot 1 | I12: =battlesetup!F2 -> Barnaby Lee | J12: HP | K12: =N8 -> 900 | M12: P1 Slot2 Mana | N12: 93
B13: Slot 2 | C13: =battlesetup!C3 -> Andre Egwu | D13: HP | E13: =N6 -> 600 | H13: Slot 2 | I13: =battlesetup!F3 -> Ben Copper | J13: HP | K13: =N9 -> 550 | M13: P1 Slot3 Mana | N13: 98
B14: Slot 3 | C14: =battlesetup!C4 -> Badeea Ali | D14: HP | E14: =N7 -> 550 | H14: Slot 3 | I14: =battlesetup!F4 -> Chiara Lobosca | J14: HP | K14: =N10 -> 700 | M14: P2 Slot1 Mana | N14: 68
M15: P2 Slot2 Mana | N15: 95
M16: P2 Slot3 Mana | N16: 80
B17: SKILL PICKER
B18: Select Skill | D18: Mana Cost | E18: =IF(C18="","",VLOOKUP(C18,skills!$B:$G,6,0))
B19: Damage Type | C19: =IF(C18="","",VLOOKUP(C18,skills!$B:$F,5,0))
B20: Skill Category | C20: =IF(C18="","",VLOOKUP(C18,skills!$B:$F,3,0))
H21: c

Sheet stats
A1: Class | B1: Tier | C1: HP | D1: DEF | E1: ATK | F1: MAG | G1: AGI | H1: INT | I1: Total
A2: Alchemist | B2: C | C2: 60 | D2: 50 | E2: 45 | F2: 70 | G2: 55 | H2: 75 | I2: 355
A3: Anti-Paladin | B3: B | C3: 80 | D3: 75 | E3: 85 | F3: 35 | G3: 35 | H3: 50 | I3: 355 | K3: 10
A4: Arcane Trickster | B4: A | C4: 75 | D4: 65 | E4: 70 | F4: 80 | G4: 90 | H4: 80 | I4: 425
A5: Assassin | B5: B | C5: 65 | D5: 55 | E5: 90 | F5: 20 | G5: 92 | H5: 65 | I5: 387
A6: Barbarian | B6: B | C6: 95 | D6: 75 | E6: 90 | F6: 10 | G6: 60 | H6: 30 | I6: 360
A7: Bard | B7: C | C7: 60 | D7: 45 | E7: 30 | F7: 80 | G7: 55 | H7: 85 | I7: 355
A8: Blood Hunter | B8: A | C8: 75 | D8: 60 | E8: 88 | F8: 45 | G8: 65 | H8: 70 | I8: 388
A9: Cleric | B9: B | C9: 70 | D9: 65 | E9: 40 | F9: 80 | G9: 40 | H9: 60 | I9: 355
A10: Druid | B10: S | C10: 90 | D10: 90 | E10: 93 | F10: 95 | G10: 95 | H10: 95 | I10: 565
A11: Fighter | B11: B | C11: 90 | D11: 85 | E11: 80 | F11: 15 | G11: 45 | H11: 35 | I11: 350
A12: Gunslinger | B12: C | C12: 60 | D12: 45 | E12: 85 | F12: 20 | G12: 85 | H12: 60 | I12: 355
A13: Monk | B13: C | C13: 70 | D13: 60 | E13: 80 | F13: 25 | G13: 85 | H13: 30 | I13: 350
A14: Necromancer | B14: A | C14: 55 | D14: 40 | E14: 25 | F14: 90 | G14: 45 | H14: 95 | I14: 350
A15: Ninja | B15: A | C15: 70 | D15: 75 | E15: 90 | F15: 30 | G15: 98 | H15: 85 | I15: 403
... A25: Wizard | B25: B | C25: 55 | D25: 45 | E25: 30 | F25: 90 | G25: 55 | H25: 90 | I25: 365

Sheet skills
A1: Class | B1: Skill Name | C1: Skill Type | D1: Skill Category | E1: Description | F1: Damage Type | G1: Mana Cost
A2: Rogue | B2: Shadow Step | C2: Active | D2: Mobility | E2: Instantly vanish and reappear behind a target or chosen location within 30 feet. Next basic attack within 2 seconds is a guaranteed Sneak Attack dealing massive bonus physical damage. | F2: Physical | G2: 15
A3: Rogue | B3: Vanish | C3: Active | D3: Defensive/Stealth | E3: Throw a smoke pellet and enter Improved Invisibility for 5 seconds. Does not break on minor damage allowing safe repositioning. | F3: None | G3: 15
A4: Rogue | B4: Lock-Pick Lunge | C4: Active | D4: Utility/Damage | E4: Strike a target's armor at its weakest point ignoring 100% physical armor and applying Sunder debuff reducing armor for all allies for 6 seconds. | F4: Physical | G4: 15
A5: Rogue | B5: Crippling Toss | C5: Active | D5: Ranged/Control | E5: Hurl a dagger at an enemy's leg dealing moderate damage and Crippling them (70% movement speed reduction for 3 seconds). Roots them if already slowed. | F5: Physical | G5: 15
A6: Rogue | B6: Thousand Cuts | C6: Active | D6: Ultimate | E6: Dash between all enemies in an area striking each up to three times. Untargetable during skill. Each strike has high chance to apply Bleed scaling with target's missing health. | F6: Physical | G6: 35
A7: Rogue | B7: Opportunist's Edge | C7: Passive | D7: - | E7: Deal 25% increased damage against Crowd Controlled enemies or targets focused on an ally. Footsteps are naturally silent reducing enemy detection range by 50%. | F7: None | G7: 0
A8: Fighter | B8: Tactical Strike | C8: Active | D8: Melee/Buff | E8: Precise blow that resets cooldown of defensive abilities on hit. Grants Combat Advantage increasing next two basic attacks' damage for 4 seconds. | F8: Physical | G8: 15
A9: Fighter | B9: Shield Bash | C9: Active | D9: Control/Defense | E9: Slam shield into enemy dealing blunt damage and Stunning for 2 seconds. Can interrupt spellcasting or push enemies away from allies. | F9: Physical | G9: 15
A10: Fighter | B10: Challenging Shout | C10: Active | D10: Taunt/Debuff | E10: Force all nearby enemies to attack the Fighter for 4 seconds. While active take 30% reduced damage from all sources. | F10: None | G10: 15
A11: Fighter | B11: Second Wind | C11: Active | D11: Sustain | E11: Instantly heal for a percentage of max health. Clears Exhaustion and movement-impairing effects. | F11: None | G11: 15
A12: Fighter | B12: Bladestorm | C12: Active | D12: Ultimate | E12: Spin weapons in a wide radius dealing massive physical damage every 0.5 seconds. Move freely at 50% speed and pull nearby enemies toward the vortex center. | F12: Physical | G12: 35
A13: Fighter | B13: Battle Hardened | C13: Passive | D13: - | E13: Gain Adrenaline stacks every 5 seconds in combat or when hit. Each stack increases Armor and Health Regeneration. At max stacks become Unstoppable (immune to knockback and interrupts). | F13: None | G13: 0
... A145: Oracle | B145: Prophetic Sight | C145: Passive | D145: - | E145: Every 15 seconds divine two random numbers (1-20) displayed on the UI. The next attack or saving throw by the Oracle or a nearby ally can spend one of these numbers to replace the result turning a miss into a critical hit or a fatal blow into a graze. | F145: None | G145: 0
